Metadata-Version: 2.1
Name: emotion-analysis
Version: 0.1.6
Summary: A package for emotion detection using transformers-based models.
Home-page: https://github.com/ahsantariq7/emotion_analysis
Author: Ahsan Tariq
Author-email: ahsantariq0724@email.com
License: MIT
Keywords: emotion analysis transformers machine learning,engr_ahsan_tariq_0724,bert_vector,roberta_vector,nlp,text emotion analysis,emotion analysis
Platform: UNKNOWN
Classifier: License :: OSI Approved :: MIT License
Classifier: Programming Language :: Python :: 3
Classifier: Programming Language :: Python :: 3.6
Classifier: Programming Language :: Python :: 3.7
Classifier: Programming Language :: Python :: 3.8
Classifier: Programming Language :: Python :: 3.9
Classifier: Operating System :: OS Independent
